dns_zone_builder/__init__.py
dns_zone_builder-0.1.8.dist-info/LICENSE.txt
dns_zone_builder-0.1.8.dist-info/METADATA
dns_zone_builder-0.1.8.dist-info/WHEEL
dns_zone_builder-0.1.8.dist-info/top_level.txt
dns_zone_builder-0.1.8.dist-info/zip-safe
dns_zone_builder-0.1.8.dist-info/RECORD
